{
	"class" : {
		"canBeRoot" : " 8/25/2016 17:45:55",
		"defaultSetUp" : " 8/25/2016 17:45:55",
		"initialize" : "maxmattone 8/25/2016 18:40",
		"newsCollection" : " 8/25/2016 17:45:55" },
	"instance" : {
		"children" : " 8/25/2016 17:45:55",
		"edit:" : " 8/25/2016 17:45:55",
		"initContent" : "maxmattone 8/25/2016 19:01",
		"initialRequest:" : "maxmattone 8/25/2016 18:34",
		"initialize" : " 8/25/2016 17:45:55",
		"remove:" : " 8/25/2016 17:45:55",
		"renderContentOn:" : " 8/25/2016 17:45:55",
		"selected" : "maxmattone 8/25/2016 18:32",
		"selected:" : " 8/25/2016 17:45:55",
		"unselect" : " 8/25/2016 17:45:55",
		"updateUrl:" : "maxmattone 8/25/2016 18:32" } }
